ec2_cluster/VERSION
ec2_cluster/__init__.py
ec2_cluster/clusterdef_params.yaml
ec2_cluster/control.py
ec2_cluster/infra.py
ec2_cluster/orch.py
ec2_cluster/utils.py
ec2_cluster-0.5.0.data/scripts/ec3
ec2_cluster-0.5.0.dist-info/METADATA
ec2_cluster-0.5.0.dist-info/WHEEL
ec2_cluster-0.5.0.dist-info/top_level.txt
ec2_cluster-0.5.0.dist-info/RECORD
