Metadata-Version: 2.1
Name: ec2-cluster
Version: 0.5.0
Summary: A tool for launching and running commands on multiple EC2 instances
Home-page: https://github.com/armandmcqueen/ec2-cluster
Author: Armand McQueen
Author-email: armandmcqueen@gmail.com
License: UNKNOWN
Platform: UNKNOWN
Classifier: Programming Language :: Python :: 3.6
Requires-Dist: paramiko (<=2.5.1)
Requires-Dist: fabric2 (>2.3.0)
Requires-Dist: boto3
Requires-Dist: pyyaml
Requires-Dist: tabulate
